LlamaDocIndexer/__init__.py
LlamaDocIndexer/indexer.py
LlamaDocIndexer/io/__init__.py
LlamaDocIndexer/io/documents.py
LlamaDocIndexer/utilities/__init__.py
LlamaDocIndexer/utilities/patterns.py
LlamaDocIndexer-0.3.3.dist-info/LICENSE
LlamaDocIndexer-0.3.3.dist-info/METADATA
LlamaDocIndexer-0.3.3.dist-info/WHEEL
LlamaDocIndexer-0.3.3.dist-info/top_level.txt
LlamaDocIndexer-0.3.3.dist-info/RECORD
