Metadata-Version: 2.2
Name: LlamaDocIndexer
Version: 0.3.3
Summary: A tool to index and monitor changes in document directories
Home-page: https://github.com/chenjiayi8/LlamaDocIndexer
Download-URL: https://pypi.org/project/LlamaDocIndexer/
Author: Jiayi Chen
Author-email: chenjiayi_344@hotmail.com
License-File: LICENSE
Requires-Dist: llama-index==0.12.16
Requires-Dist: xlrd==2.0.1
Requires-Dist: python_dotenv==1.0.0
Dynamic: author
Dynamic: author-email
Dynamic: description-content-type
Dynamic: download-url
Dynamic: home-page
Dynamic: requires-dist
Dynamic: summary
